dummy.servoarray-0-armv6l-gnu_linux.so
libservoarray.so
servoarray.cpython-37m-arm-linux-gnueabihf.so
servoarray-0.7.0.dist-info/COPYING
servoarray-0.7.0.dist-info/METADATA
servoarray-0.7.0.dist-info/WHEEL
servoarray-0.7.0.dist-info/top_level.txt
servoarray-0.7.0.dist-info/RECORD
