Metadata-Version: 2.1
Name: servoarray
Version: 0.7.0
Summary: ServoArray: Pluggable servomotor driver library
Home-page: UNKNOWN
Author: coord.e
Author-email: me@coord-e.com
License: UNKNOWN
Platform: UNKNOWN
Classifier: Development Status :: 4 - Beta
Classifier: Intended Audience :: Developers
Classifier: Environment :: Other Environment
Classifier: License :: OSI Approved :: GNU General Public License v2 (GPLv2)
Classifier: Operating System :: POSIX
Classifier: Programming Language :: Python
Classifier: Programming Language :: C++
Classifier: Topic :: Software Development :: Libraries
Classifier: Topic :: Software Development :: Embedded Systems
Classifier: Topic :: System :: Hardware :: Hardware Drivers
